{"BasePath":null,"Description":"Gx On Pending Event Failed","EntryPointMethods":[],"FullName":"General.Services.GxOnPendingEventFailed","GrpcNameSpace":"","HasGAM":false,"IsAPI":false,"IsBC":false,"IsDP":false,"IsGrpc":false,"IsSD":false,"IsSDT":false,"IsSvc":false,"Name":"GxOnPendingEventFailed","Parameters":[{"Alias":"","CollectionItemName":"SynchronizationEventListItem","Decimals":0,"DefaultValue":null,"Description":"Synchronization Event List","FullName":null,"Inout":1,"IsBCSDT":false,"IsCollection":true,"IsFilterAtt":false,"IsKey":false,"IsNullable":false,"IsPathParameter":false,"Length":0,"Name":"PendingEvent","SDTType":"GeneXus.SD.Synchronization.SynchronizationEventList","Sign":0,"Type":0},{"Alias":"","CollectionItemName":null,"Decimals":0,"DefaultValue":null,"Description":null,"FullName":null,"Inout":1,"IsBCSDT":false,"IsCollection":false,"IsFilterAtt":false,"IsKey":false,"IsNullable":false,"IsPathParameter":false,"Length":128,"Name":"BCName","SDTType":null,"Sign":0,"Type":13},{"Alias":"","CollectionItemName":null,"Decimals":0,"DefaultValue":null,"Description":null,"FullName":null,"Inout":1,"IsBCSDT":false,"IsCollection":false,"IsFilterAtt":false,"IsKey":false,"IsNullable":false,"IsPathParameter":false,"Length":2097152,"Name":"BCJson","SDTType":null,"Sign":0,"Type":8},{"Alias":"","CollectionItemName":"SynchronizationEventResultListItem","Decimals":0,"DefaultValue":null,"Description":"Synchronization Event Result List","FullName":null,"Inout":1,"IsBCSDT":false,"IsCollection":true,"IsFilterAtt":false,"IsKey":false,"IsNullable":false,"IsPathParameter":false,"Length":0,"Name":"EventResult","SDTType":"GeneXus.SD.Synchronization.SynchronizationEventResultList","Sign":0,"Type":0},{"Alias":"","CollectionItemName":null,"Decimals":0,"DefaultValue":null,"Description":"Synchronization Info","FullName":null,"Inout":1,"IsBCSDT":false,"IsCollection":false,"IsFilterAtt":false,"IsKey":false,"IsNullable":false,"IsPathParameter":false,"Length":0,"Name":"GxSyncroInfo","SDTType":"GeneXus.SD.Synchronization.SynchronizationInfo","Sign":0,"Type":0},{"Alias":"","CollectionItemName":null,"Decimals":0,"DefaultValue":null,"Description":null,"FullName":null,"Inout":2,"IsBCSDT":false,"IsCollection":false,"IsFilterAtt":false,"IsKey":false,"IsNullable":false,"IsPathParameter":false,"Length":4,"Name":"Continue","SDTType":null,"Sign":0,"Type":15}],"SDT":null,"isOData":false,"isOpenAPI":true,"isUseEnvironmentPropertyValueOpenAPI":true,"openAPIVersion":""}